lenzyai/__init__.py
lenzyai/client.py
lenzyai/py.typed
lenzyai/types.py
lenzyai-0.0.5.dist-info/licenses/LICENSE
lenzyai-0.0.5.dist-info/METADATA
lenzyai-0.0.5.dist-info/WHEEL
lenzyai-0.0.5.dist-info/top_level.txt
lenzyai-0.0.5.dist-info/RECORD
